async_slack/__init__.py
async_slack/channel_grouper.py
async_slack/channels_graph.py
async_slack/config.py
async_slack/convert_to_org_graph.py
async_slack/date_utils.py
async_slack/db.py
async_slack/dict_utils.py
async_slack/enriched_messages_graph.py
async_slack/message_count_graph.py
async_slack/messages_fetcher.py
async_slack/orger/__init__.py
async_slack/orger/inorganic.py
async_slack/raw_threads_graph.py
async_slack/slack.py
async_slack/update_database.py
async_slack/users_graph.py
async_slack-0.1.0rc3.dist-info/entry_points.txt
async_slack-0.1.0rc3.dist-info/WHEEL
async_slack-0.1.0rc3.dist-info/METADATA
async_slack-0.1.0rc3.dist-info/RECORD
