Metadata-Version: 2.1
Name: async-slack
Version: 0.1.0rc3
Summary: 
Author: Pascal Bugnion
Author-email: pascal@bugnion.org
Requires-Python: >=3.6,<4.0
Classifier: Programming Language :: Python :: 3
Classifier: Programming Language :: Python :: 3.6
Classifier: Programming Language :: Python :: 3.7
Classifier: Programming Language :: Python :: 3.8
Requires-Dist: bonobo (>=0.6.4,<0.7.0)
Requires-Dist: dpath (>=2.0.1,<3.0.0)
Requires-Dist: emoji (>=0.5.4,<0.6.0)
Requires-Dist: slacker (>=0.14.0,<0.15.0)
Requires-Dist: tenacity (>=6.1.0,<7.0.0)
Requires-Dist: toml (>=0.10.0,<0.11.0)
Requires-Dist: workalendar (>=8.4.0,<9.0.0)
